splurge_data_profiler/__init__.py
splurge_data_profiler/__main__.py
splurge_data_profiler/cli.py
splurge_data_profiler/data_lake.py
splurge_data_profiler/exceptions.py
splurge_data_profiler/profiler.py
splurge_data_profiler/source.py
splurge_data_profiler-2025.2.0.dist-info/licenses/LICENSE
splurge_data_profiler-2025.2.0.dist-info/METADATA
splurge_data_profiler-2025.2.0.dist-info/WHEEL
splurge_data_profiler-2025.2.0.dist-info/entry_points.txt
splurge_data_profiler-2025.2.0.dist-info/top_level.txt
splurge_data_profiler-2025.2.0.dist-info/RECORD
