Metadata-Version: 2.4
Name: splurge-data-profiler
Version: 2025.2.0
Summary: A data profiling tool for delimited and database sources.
Author: Jim Schilling
Maintainer: Jim Schilling
License-Expression: MIT
Project-URL: Homepage, https://github.com/jim-schilling/splurge-data-profiler
Project-URL: Documentation, https://github.com/jim-schilling/splurge-data-profiler/blob/main/docs/README-details.md
Project-URL: Repository, https://github.com/jim-schilling/splurge-data-profiler.git
Project-URL: Issues, https://github.com/jim-schilling/splurge-data-profiler/issues
Project-URL: Changelog, https://github.com/jim-schilling/splurge-data-profiler/blob/main/CHANGELOG.md
Keywords: data-profiling,csv,tsv,dsv,data-lake,sqlite,type-inference,data-analysis,etl,data-processing
Classifier: Development Status :: 3 - Alpha
Classifier: Intended Audience :: Developers
Classifier: Operating System :: OS Independent
Classifier: Programming Language :: Python :: 3
Classifier: Programming Language :: Python :: 3.10
Classifier: Programming Language :: Python :: 3.11
Classifier: Programming Language :: Python :: 3.12
Classifier: Topic :: Database
Classifier: Topic :: Scientific/Engineering :: Information Analysis
Classifier: Topic :: Software Development :: Libraries :: Python Modules
Classifier: Topic :: Text Processing :: Filters
Requires-Python: >=3.10
License-File: LICENSE
Requires-Dist: sqlalchemy>=2.0.37
Requires-Dist: splurge-dsv>=2025.1.5
Requires-Dist: splurge-typer>=2025.0.1
Requires-Dist: splurge-tabular>=2025.0.0
Provides-Extra: test
Requires-Dist: pytest>=7.0.0; extra == "test"
Requires-Dist: pytest-cov>=4.0.0; extra == "test"
Requires-Dist: pytest-xdist>=3.8.0; extra == "test"
Provides-Extra: dev
Requires-Dist: pytest>=7.0.0; extra == "dev"
Requires-Dist: pytest-cov>=4.0.0; extra == "dev"
Requires-Dist: pytest-xdist>=3.8.0; extra == "dev"
Requires-Dist: ruff>=0.12.12; extra == "dev"
Requires-Dist: mypy>=1.0.0; extra == "dev"
Dynamic: license-file
